symjoy/__init__.py
symjoy/api/__init__.py
symjoy/api/arrows.py
symjoy/api/currency.py
symjoy/api/emoji.py
symjoy/api/math.py
symjoy/api/misc.py
symjoy/api/symbols.py
symjoy/categories/arrows.py
symjoy/categories/currency.py
symjoy/categories/emoji.py
symjoy/categories/math.py
symjoy/categories/misc.py
symjoy/categories/symbols.py
symjoy/core/registry.py
symjoy/core/search.py
symjoy-2.1.0.dist-info/METADATA
symjoy-2.1.0.dist-info/WHEEL
symjoy-2.1.0.dist-info/licenses/LICENSE
symjoy-2.1.0.dist-info/RECORD
