Metadata-Version: 2.4
Name: symjoy
Version: 2.1.0
Summary: The unicode_symbols package is designed to simplify the use of Unicode characters in Python projects. Whether you need emojis for chat applications, symbols for documentation, mathematical symbols for calculations, currency symbols for finance apps, or miscellaneous icons for fun, this package has you covered.
Project-URL: Homepage, https://github.com/vishwanathdvgmm/symjoy
Project-URL: Issues, https://github.com/vishwanathdvgmm/symjoy/issues
Author-email: Vishwanath M M <vishwanathmm2005@gmail.com>
License-Expression: MIT
License-File: LICENSE
Classifier: Operating System :: OS Independent
Classifier: Programming Language :: Python :: 3
Requires-Python: >=3.12
